lefschetz_family/__init__.py
lefschetz_family/allowableLoops.py
lefschetz_family/calabiYauOperator.py
lefschetz_family/calabiYauOperatorOld.py
lefschetz_family/context.py
lefschetz_family/delaunay.py
lefschetz_family/delaunayDual.py
lefschetz_family/doubleCover.py
lefschetz_family/ellipticSingularity.py
lefschetz_family/ellipticSurface.py
lefschetz_family/exceptionalDivisorComputer.py
lefschetz_family/exceptions.py
lefschetz_family/fibration.py
lefschetz_family/fibreProduct.py
lefschetz_family/hypersurface.py
lefschetz_family/integrator.py
lefschetz_family/integrator_simultaneous.py
lefschetz_family/monodromyRepresentation.py
lefschetz_family/monodromyRepresentationCurve.py
lefschetz_family/monodromyRepresentationEllipticSurface.py
lefschetz_family/monodromyRepresentationFiberedProduct.py
lefschetz_family/monodromyRepresentationGeneric.py
lefschetz_family/monodromyRepresentationSurface.py
lefschetz_family/pointed_loops.py
lefschetz_family/rootsBraid.py
lefschetz_family/simul_integrator_function.py
lefschetz_family/toricCY3.py
lefschetz_family/translator.py
lefschetz_family/util.py
lefschetz_family/voronoi.py
lefschetz_family/numperiods/cohomology.py
lefschetz_family/numperiods/config.py
lefschetz_family/numperiods/family.py
lefschetz_family/numperiods/familyNew.py
lefschetz_family/numperiods/integerRelations.py
lefschetz_family/numperiods/interpolation.py
lefschetz_family-0.1.19.dist-info/METADATA
lefschetz_family-0.1.19.dist-info/WHEEL
lefschetz_family-0.1.19.dist-info/licenses/LICENSE
lefschetz_family-0.1.19.dist-info/RECORD
