Metadata-Version: 2.4
Name: lefschetz-family
Version: 0.1.19
Summary: This package implements algorithms relying on Lefschetz fibration theory to compute periods of algebraic varieties.
Project-URL: Homepage, https://github.com/ericpipha/lefschetz-family
Project-URL: Bug Tracker, https://github.com/ericpipha/lefschetz-family
Author-email: Eric Pichon-Pharabod <eric.pichon@mis.mpg.de>
License-File: LICENSE
Classifier: License :: OSI Approved :: MIT License
Classifier: Operating System :: OS Independent
Classifier: Programming Language :: Python :: 3
Requires-Python: >=3.7
Requires-Dist: delaunay-triangulation
Requires-Dist: ore-algebra
Provides-Extra: passagemath
Requires-Dist: passagemath-combinat; extra == 'passagemath'
Requires-Dist: passagemath-flint; extra == 'passagemath'
Requires-Dist: passagemath-graphs; extra == 'passagemath'
Requires-Dist: passagemath-groups; extra == 'passagemath'
Requires-Dist: passagemath-modules; extra == 'passagemath'
Requires-Dist: passagemath-pari; extra == 'passagemath'
Requires-Dist: passagemath-polyhedra; extra == 'passagemath'
Requires-Dist: passagemath-repl; extra == 'passagemath'
Requires-Dist: passagemath-schemes; extra == 'passagemath'
Requires-Dist: passagemath-symbolics; extra == 'passagemath'
Requires-Dist: scipy; extra == 'passagemath'
